miniofs/__init__.py
miniofs/config.yml
miniofs/functional.py
miniofs-0.0.4.dist-info/LICENSE
miniofs-0.0.4.dist-info/METADATA
miniofs-0.0.4.dist-info/WHEEL
miniofs-0.0.4.dist-info/top_level.txt
miniofs-0.0.4.dist-info/RECORD
