Metadata-Version: 2.1
Name: miniofs
Version: 0.0.4
Summary: Minio Tools for python
Home-page: https://github.com/JeanMaximilienCadic/miniofs
Author: Jean Maximilien Cadic
Author-email: git@cadic.jp
License: MIT
Classifier: Programming Language :: Python :: 3.6
Classifier: License :: OSI Approved :: MIT License
Requires-Python: >=3.6
License-File: LICENSE
Requires-Dist: minio
Requires-Dist: gnutools-python
